{"version":1,"resource":"file:///d%3A/Projects/AssaignMent_phero/ShareMeal/clientSide/src/components/Cards.jsx","entries":[{"id":"Be64.jsx","timestamp":1709692681592},{"id":"1ODn.jsx","timestamp":1709827124876},{"id":"qxw7.jsx","timestamp":1709827158684},{"id":"HGMR.jsx","source":"Workspace Edit","timestamp":1709827168505},{"id":"JZsN.jsx","source":"Workspace Edit","timestamp":1709827181247},{"id":"ttFn.jsx","timestamp":1709827197860},{"id":"uMwk.jsx","source":"moved.source","timestamp":1709833015601},{"id":"5my3.jsx","source":"moved.source","timestamp":1709833038973}]}