{"version":1,"resource":"file:///d%3A/Projects/HarvestHub/ClientSide/src/components/Hero.jsx","entries":[{"id":"5NC6.jsx","timestamp":1711772666228},{"id":"S4sN.jsx","timestamp":1711772762618},{"id":"4uwR.jsx","source":"Workspace Edit","timestamp":1711772839537},{"id":"izTb.jsx","source":"undoRedo.source","timestamp":1711772940747},{"id":"EBgs.jsx","timestamp":1711773547597},{"id":"jptd.jsx","timestamp":1711773615056},{"id":"8pKj.jsx","timestamp":1711773646703},{"id":"2M9o.jsx","timestamp":1711773936123},{"id":"2iLI.jsx","timestamp":1711773988558},{"id":"4UeE.jsx","timestamp":1711773999772}]}